setup.py
AADeepLearning/__init__.py
AADeepLearning/aadeeplearning.py
AADeepLearning/config.py
AADeepLearning/activation/__init__.py
AADeepLearning/activation/relu.py
AADeepLearning/activation/sigmoid.py
AADeepLearning/activation/tanh.py
AADeepLearning/datasets/__init__.py
AADeepLearning/datasets/cifar.py
AADeepLearning/datasets/cifar10.py
AADeepLearning/datasets/cifar100.py
AADeepLearning/datasets/data_utils.py
AADeepLearning/datasets/fashion_mnist.py
AADeepLearning/datasets/generic_utils.py
AADeepLearning/datasets/imdb.py
AADeepLearning/datasets/mnist.py
AADeepLearning/datasets/np_utils.py
AADeepLearning/datasets/reuters.py
AADeepLearning/layer/__init__.py
AADeepLearning/layer/batch_normalization.py
AADeepLearning/layer/convolutional.py
AADeepLearning/layer/dropout.py
AADeepLearning/layer/flatten.py
AADeepLearning/layer/fully_connected.py
AADeepLearning/layer/lstm.py
AADeepLearning/layer/lstm_2.py
AADeepLearning/layer/lstm_3.py
AADeepLearning/layer/pooling.py
AADeepLearning/layer/rnn.py
AADeepLearning/loss/__init__.py
AADeepLearning/loss/softmax.py
AADeepLearning/loss/svm.py
AADeepLearning/optimizer/__init__.py
AADeepLearning/optimizer/adam.py
AADeepLearning/optimizer/momentum.py
AADeepLearning/optimizer/rmsprop.py
AADeepLearning/optimizer/sgd.py
AAdeepLearning.egg-info/PKG-INFO
AAdeepLearning.egg-info/SOURCES.txt
AAdeepLearning.egg-info/dependency_links.txt
AAdeepLearning.egg-info/requires.txt
AAdeepLearning.egg-info/top_level.txt
develop/__init__.py
develop/aa_cnn_cifar10.py
develop/aa_cnn_mnist.py
develop/aa_continue_train.py
develop/aa_dataset.py
develop/aa_dnn_cifar10.py
develop/aa_dnn_mnist.py
develop/aa_dnn_mnist_batch_normalization.py
develop/aa_dnn_mnist_drop_out.py
develop/aa_dnn_mnist_svm.py
develop/aa_lstm_letter.py
develop/aa_lstm_mnist.py
develop/aa_reload.py
develop/aa_rnn_letter.py
develop/aa_rnn_mnist.py
develop/aa_save.py
develop/aa_visualization_accuracy.py
develop/aa_visualization_loss.py
example/__init__.py
example/aa_cnn_cifar10.py
example/aa_cnn_mnist.py
example/aa_continue_train.py
example/aa_dataset.py
example/aa_dnn_cifar10.py
example/aa_dnn_mnist.py
example/aa_dnn_mnist_batch_normalization.py
