Metadata-Version: 1.0
Name: AAdeepLearning
Version: 1.0.7
Summary: AAdeepLearning is a deep learning frame
Home-page: https://github.com/luojiangtao/aadeeplearning
Author: luojiangtao
Author-email: 1368761119@qq.com
License: MIT Licence
Keywords: AAdeepLearning,AA,deepLearning frame
Platform: any
